featuremesh/__init__.py
featuremesh/access.py
featuremesh/client.py
featuremesh/config.py
featuremesh/display.py
featuremesh/magic.py
featuremesh/results.py
featuremesh/utils/__init__.py
featuremesh/utils/utils_client.py
featuremesh/utils/utils_slt.py
featuremesh-0.1.2.dist-info/METADATA
featuremesh-0.1.2.dist-info/WHEEL
featuremesh-0.1.2.dist-info/top_level.txt
featuremesh-0.1.2.dist-info/RECORD
