Metadata-Version: 2.4
Name: featuremesh
Version: 0.1.2
Summary: Python client for FeatureMesh - Execute FeatureQL queries on multiple database backends
Author-email: FeatureMesh <info@featuremesh.com>
License-Expression: MIT
Project-URL: Homepage, https://featuremesh.com
Project-URL: Repository, https://github.com/featuremesh/featuremesh-client-py
Keywords: featureql,featuremesh,sql,data,query,duckdb,trino,bigquery
Classifier: Development Status :: 3 - Alpha
Classifier: Intended Audience :: Developers
Classifier: Programming Language :: Python :: 3
Classifier: Programming Language :: Python :: 3.9
Classifier: Programming Language :: Python :: 3.10
Classifier: Programming Language :: Python :: 3.11
Classifier: Programming Language :: Python :: 3.12
Classifier: Programming Language :: Python :: 3.13
Classifier: Operating System :: OS Independent
Classifier: Topic :: Database
Classifier: Topic :: Software Development :: Libraries :: Python Modules
Classifier: Typing :: Typed
Requires-Python: >=3.9
Requires-Dist: requests>=2.31.0
Requires-Dist: pandas>=2.0.0
Requires-Dist: ipython>=7.0.0
Requires-Dist: numpy>=1.22.0
Provides-Extra: duckdb
Requires-Dist: duckdb>=1.0.0; extra == "duckdb"
Provides-Extra: trino
Requires-Dist: trino>=0.320.0; extra == "trino"
Provides-Extra: bigquery
Requires-Dist: google-cloud-bigquery>=3.0.0; extra == "bigquery"
Provides-Extra: datafusion
Requires-Dist: datafusion>=40.0.0; extra == "datafusion"
Provides-Extra: all
Requires-Dist: duckdb>=1.0.0; extra == "all"
Requires-Dist: trino>=0.320.0; extra == "all"
Requires-Dist: google-cloud-bigquery>=3.0.0; extra == "all"
Requires-Dist: datafusion>=40.0.0; extra == "all"
